rasp/__init__.py
rasp/main.py
triware-1.0.2.dist-info/DESCRIPTION.rst
triware-1.0.2.dist-info/METADATA
triware-1.0.2.dist-info/RECORD
triware-1.0.2.dist-info/WHEEL
triware-1.0.2.dist-info/metadata.json
triware-1.0.2.dist-info/top_level.txt
